codex_rule_server/tool.py
codex_rule_server-0.1.0.dist-info/METADATA
codex_rule_server-0.1.0.dist-info/WHEEL
codex_rule_server-0.1.0.dist-info/top_level.txt
codex_rule_server-0.1.0.dist-info/RECORD
