Metadata-Version: 2.4
Name: codex-rule-server
Version: 0.1.0
Summary: 规则文件操作
Requires-Python: >=3.13
Requires-Dist: mcp>=1.12.2
Requires-Dist: pydantic>=2.11.7
Requires-Dist: requests>=2.32.4
